{
  "action": {
    "description": "CR; Do Pass, amended by committee substitute Energy and Natural Resources Oversight Committee",
    "occurred_at": "2025-02-26",
    "jurisdiction_id": "~{\"classification\": \"lower\"}",
    "session_id": "2026",
    "entity_type": "bill",
    "classifications": [
      "committee-passage"
    ],
    "related_entities": [],
    "sources": [
      {
        "url": "http://www.oklegislature.gov/BillInfo.aspx?Bill=HB2752&session=2600",
        "note": ""
      }
    ]
  },
  "bill_id": "HB2752"
}