{
  "legislative_session": "2026",
  "identifier": "SB1410",
  "title": "Agriculture; requiring operation of an Ag in the Classroom Education Program; requiring development of curriculum for K-12 programs. Effective date.",
  "from_organization": "~{\"classification\": \"upper\"}",
  "classification": [
    "bill"
  ],
  "subject": [],
  "abstracts": [],
  "other_titles": [],
  "other_identifiers": [
    {
      "identifier": "ocd-bill-ok-2026-sb1410"
    }
  ],
  "actions": [
    {
      "description": "First Reading",
      "date": "2026-02-02",
      "organization_id": "~{\"classification\": \"upper\"}",
      "classification": [
        "introduction",
        "reading-1"
      ],
      "related_entities": [],
      "_processing": {
        "log_file_created": "2026-07-13T06:04:21Z"
      }
    },
    {
      "description": "Authored by Senator Jech",
      "date": "2026-02-02",
      "organization_id": "~{\"classification\": \"upper\"}",
      "classification": [],
      "related_entities": [],
      "_processing": {
        "log_file_created": "2026-07-13T06:04:21Z"
      }
    },
    {
      "description": "Second Reading referred to Education Committee then to Appropriations Committee",
      "date": "2026-02-03",
      "organization_id": "~{\"classification\": \"upper\"}",
      "classification": [
        "reading-2",
        "referral-committee"
      ],
      "related_entities": [],
      "_processing": {
        "log_file_created": "2026-07-15T13:05:31Z"
      }
    },
    {
      "description": "Coauthored by Representative Patzkowsky (principal House author)",
      "date": "2026-02-11",
      "organization_id": "~{\"classification\": \"upper\"}",
      "classification": [],
      "related_entities": [],
      "_processing": {
        "log_file_created": "2026-07-15T13:05:31Z"
      }
    },
    {
      "description": "Coauthored by Senator Pederson",
      "date": "2026-02-17",
      "organization_id": "~{\"classification\": \"upper\"}",
      "classification": [],
      "related_entities": [],
      "_processing": {
        "log_file_created": "2026-07-15T13:05:31Z"
      }
    },
    {
      "description": "Reported Do Pass as amended Education committee; CR filed",
      "date": "2026-02-17",
      "organization_id": "~{\"classification\": \"upper\"}",
      "classification": [
        "committee-passage"
      ],
      "related_entities": [],
      "_processing": {
        "log_file_created": "2026-07-15T13:05:31Z"
      }
    },
    {
      "description": "Title stricken",
      "date": "2026-02-17",
      "organization_id": "~{\"classification\": \"upper\"}",
      "classification": [],
      "related_entities": [],
      "_processing": {
        "log_file_created": "2026-07-15T13:05:31Z"
      }
    },
    {
      "description": "Referred to Appropriations",
      "date": "2026-02-17",
      "organization_id": "~{\"classification\": \"upper\"}",
      "classification": [
        "referral-committee"
      ],
      "related_entities": [],
      "_processing": {
        "log_file_created": "2026-07-15T13:05:31Z"
      }
    },
    {
      "description": "Withdrawn from Appropriations committee",
      "date": "2026-02-23",
      "organization_id": "~{\"classification\": \"upper\"}",
      "classification": [],
      "related_entities": [],
      "_processing": {
        "log_file_created": "2026-07-15T13:05:31Z"
      }
    },
    {
      "description": "Placed on General Order",
      "date": "2026-02-23",
      "organization_id": "~{\"classification\": \"upper\"}",
      "classification": [],
      "related_entities": [],
      "_processing": {
        "log_file_created": "2026-07-15T13:05:31Z"
      }
    },
    {
      "description": "General Order, Amended",
      "date": "2026-03-26",
      "organization_id": "~{\"classification\": \"upper\"}",
      "classification": [],
      "related_entities": [],
      "_processing": {
        "log_file_created": "2026-07-15T13:05:31Z"
      }
    },
    {
      "description": "Title restored",
      "date": "2026-03-26",
      "organization_id": "~{\"classification\": \"upper\"}",
      "classification": [],
      "related_entities": [],
      "_processing": {
        "log_file_created": "2026-07-15T13:05:31Z"
      }
    },
    {
      "description": "Measure passed:  Ayes: 41  Nays: 0",
      "date": "2026-03-26",
      "organization_id": "~{\"classification\": \"upper\"}",
      "classification": [
        "passage"
      ],
      "related_entities": [],
      "_processing": {
        "log_file_created": "2026-07-15T13:05:31Z"
      }
    },
    {
      "description": "Referred for engrossment",
      "date": "2026-03-26",
      "organization_id": "~{\"classification\": \"upper\"}",
      "classification": [],
      "related_entities": [],
      "_processing": {
        "log_file_created": "2026-07-15T13:05:31Z"
      }
    },
    {
      "description": "Engrossed to House",
      "date": "2026-03-30",
      "organization_id": "~{\"classification\": \"upper\"}",
      "classification": [
        "passage"
      ],
      "related_entities": [],
      "_processing": {
        "log_file_created": "2026-07-15T13:05:31Z"
      }
    },
    {
      "description": "First Reading",
      "date": "2026-03-30",
      "organization_id": "~{\"classification\": \"lower\"}",
      "classification": [
        "introduction",
        "reading-1"
      ],
      "related_entities": [],
      "_processing": {
        "log_file_created": "2026-07-15T13:05:31Z"
      }
    },
    {
      "description": "Second Reading referred to Education Oversight",
      "date": "2026-03-31",
      "organization_id": "~{\"classification\": \"lower\"}",
      "classification": [
        "reading-2",
        "referral-committee"
      ],
      "related_entities": [],
      "_processing": {
        "log_file_created": "2026-07-15T13:05:31Z"
      }
    },
    {
      "description": "Referred to Common Education",
      "date": "2026-03-31",
      "organization_id": "~{\"classification\": \"lower\"}",
      "classification": [
        "referral-committee"
      ],
      "related_entities": [],
      "_processing": {
        "log_file_created": "2026-07-15T13:05:31Z"
      }
    },
    {
      "description": "Policy recommendation to the Education Oversight committee; Do Pass Common Education",
      "date": "2026-04-06",
      "organization_id": "~{\"classification\": \"lower\"}",
      "classification": [
        "committee-passage"
      ],
      "related_entities": [],
      "_processing": {
        "log_file_created": "2026-07-15T13:05:31Z"
      }
    },
    {
      "description": "CR; Do Pass Education Oversight Committee",
      "date": "2026-05-05",
      "organization_id": "~{\"classification\": \"lower\"}",
      "classification": [
        "committee-passage"
      ],
      "related_entities": [],
      "_processing": {
        "log_file_created": "2026-07-15T13:05:31Z"
      }
    },
    {
      "description": "General Order",
      "date": "2026-05-06",
      "organization_id": "~{\"classification\": \"lower\"}",
      "classification": [],
      "related_entities": [],
      "_processing": {
        "log_file_created": "2026-07-15T13:05:31Z"
      }
    },
    {
      "description": "Third Reading, Measure passed:  Ayes: 88 Nays: 0",
      "date": "2026-05-06",
      "organization_id": "~{\"classification\": \"lower\"}",
      "classification": [
        "passage",
        "reading-3"
      ],
      "related_entities": [],
      "_processing": {
        "log_file_created": "2026-07-15T13:05:31Z"
      }
    },
    {
      "description": "Signed, returned to Senate",
      "date": "2026-05-06",
      "organization_id": "~{\"classification\": \"lower\"}",
      "classification": [],
      "related_entities": [],
      "_processing": {
        "log_file_created": "2026-07-15T13:05:31Z"
      }
    },
    {
      "description": "Referred for enrollment",
      "date": "2026-05-06",
      "organization_id": "~{\"classification\": \"upper\"}",
      "classification": [],
      "related_entities": [],
      "_processing": {
        "log_file_created": "2026-07-15T13:05:31Z"
      }
    },
    {
      "description": "Enrolled, to House",
      "date": "2026-05-06",
      "organization_id": "~{\"classification\": \"upper\"}",
      "classification": [],
      "related_entities": [],
      "_processing": {
        "log_file_created": "2026-07-15T13:05:31Z"
      }
    },
    {
      "description": "Signed, returned to Senate",
      "date": "2026-05-06",
      "organization_id": "~{\"classification\": \"lower\"}",
      "classification": [],
      "related_entities": [],
      "_processing": {
        "log_file_created": "2026-07-15T13:05:31Z"
      }
    },
    {
      "description": "Sent to Governor",
      "date": "2026-05-06",
      "organization_id": "~{\"classification\": \"upper\"}",
      "classification": [
        "executive-receipt"
      ],
      "related_entities": [],
      "_processing": {
        "log_file_created": "2026-07-15T13:05:31Z"
      }
    },
    {
      "description": "Approved by Governor 05/12/2026",
      "date": "2026-05-13",
      "organization_id": "~{\"classification\": \"upper\"}",
      "classification": [
        "executive-signature"
      ],
      "related_entities": [],
      "_processing": {
        "log_file_created": "2026-07-15T13:05:31Z"
      }
    }
  ],
  "sponsorships": [
    {
      "name": "Jech",
      "classification": "primary",
      "entity_type": "person",
      "primary": true,
      "person_id": "~{\"name\": \"Jech\"}",
      "organization_id": null
    },
    {
      "name": "Patzkowsky",
      "classification": "primary",
      "entity_type": "person",
      "primary": true,
      "person_id": "~{\"name\": \"Patzkowsky\"}",
      "organization_id": null
    }
  ],
  "related_bills": [],
  "versions": [
    {
      "note": "Introduced",
      "links": [
        {
          "url": "https://www.oklegislature.gov/cf_pdf/2025-26 INT/SB/SB1410 INT.PDF",
          "media_type": "application/pdf"
        }
      ],
      "date": "",
      "classification": ""
    },
    {
      "note": "Floor (House)",
      "links": [
        {
          "url": "https://www.oklegislature.gov/cf_pdf/2025-26 FLR/HFLR/SB1410 HFLR.PDF",
          "media_type": "application/pdf"
        }
      ],
      "date": "",
      "classification": ""
    },
    {
      "note": "Floor (Senate)",
      "links": [
        {
          "url": "https://www.oklegislature.gov/cf_pdf/2025-26 FLR/SFLR/SB1410 SFLR.PDF",
          "media_type": "application/pdf"
        }
      ],
      "date": "",
      "classification": ""
    },
    {
      "note": "Engrossed",
      "links": [
        {
          "url": "https://www.oklegislature.gov/cf_pdf/2025-26 ENGR/SB/SB1410 ENGR.PDF",
          "media_type": "application/pdf"
        }
      ],
      "date": "",
      "classification": ""
    },
    {
      "note": "Enrolled (final version)",
      "links": [
        {
          "url": "https://www.oklegislature.gov/cf_pdf/2025-26 ENR/SB/SB1410 ENR.PDF",
          "media_type": "application/pdf"
        }
      ],
      "date": "",
      "classification": ""
    },
    {
      "note": "SB1410 (3-17-26) (JECH) RT FA1.PDF",
      "links": [
        {
          "url": "https://www.oklegislature.gov/cf_pdf/2025-26 FLOOR AMENDMENTS/Senate/SB1410 (3-17-26) (JECH) RT FA1.PDF",
          "media_type": "application/pdf"
        }
      ],
      "date": "",
      "classification": ""
    },
    {
      "note": "Committee Amendment 1",
      "links": [
        {
          "url": "https://www.oklegislature.gov/cf_pdf/2025-26 COMMITTEE AMENDMENTS/Senate/SB1410 CA1.PDF",
          "media_type": "application/pdf"
        }
      ],
      "date": "",
      "classification": ""
    }
  ],
  "documents": [
    {
      "note": "House Policy Committee Report",
      "links": [
        {
          "url": "https://www.oklegislature.gov/cf_pdf/2025-26 COMMITTEE REPORTS/HOUSE/SB1410 POLHCR.PDF",
          "media_type": "application/pdf"
        }
      ],
      "date": "",
      "classification": ""
    },
    {
      "note": "House Committee Report",
      "links": [
        {
          "url": "https://www.oklegislature.gov/cf_pdf/2025-26 COMMITTEE REPORTS/HOUSE/SB1410 HCR.PDF",
          "media_type": "application/pdf"
        }
      ],
      "date": "",
      "classification": ""
    },
    {
      "note": "Senate Committee Report",
      "links": [
        {
          "url": "https://www.oklegislature.gov/cf_pdf/2025-26 COMMITTEE REPORTS/SENATE/SB1410 SCR.PDF",
          "media_type": "application/pdf"
        }
      ],
      "date": "",
      "classification": ""
    }
  ],
  "citations": [],
  "sources": [
    {
      "url": "http://www.oklegislature.gov/BillInfo.aspx?Bill=SB1410&session=2600",
      "note": ""
    }
  ],
  "extras": {},
  "jurisdiction": {
    "id": "ocd-jurisdiction/country:us/state:ok/government",
    "name": "Oklahoma",
    "classification": "state",
    "division_id": "ocd-division/country:us/state:ok"
  },
  "_processing": {
    "logs_latest_update": "2026-07-15T13:05:31Z",
    "text_extraction_latest_update": "2026-07-15T20:23:37.242713Z"
  }
}